Eir/__init__.py
Eir/exceptions.py
Eir/utility.py
Eir/DTMC/__init__.py
Eir/DTMC/spatialModel/HubModel.py
Eir/DTMC/spatialModel/StrongInfectiousModel.py
Eir/DTMC/spatialModel/__init__.py
Eir/DTMC/spatialModel/simul_details.py
Eir/DTMC/spatialModel/spatial.py
Eir/DTMC/spatialModel/Hub/HubSEIR.py
Eir/DTMC/spatialModel/Hub/HubSEIRD.py
Eir/DTMC/spatialModel/Hub/HubSEIRS.py
Eir/DTMC/spatialModel/Hub/HubSEIRSD.py
Eir/DTMC/spatialModel/Hub/HubSEIRSV.py
Eir/DTMC/spatialModel/Hub/HubSEIRSVD.py
Eir/DTMC/spatialModel/Hub/HubSEIRV.py
Eir/DTMC/spatialModel/Hub/HubSEIRVD.py
Eir/DTMC/spatialModel/Hub/HubSIR.py
Eir/DTMC/spatialModel/Hub/HubSIRD.py
Eir/DTMC/spatialModel/Hub/HubSIRS.py
Eir/DTMC/spatialModel/Hub/HubSIRSD.py
Eir/DTMC/spatialModel/Hub/HubSIRSV.py
Eir/DTMC/spatialModel/Hub/HubSIRSVD.py
Eir/DTMC/spatialModel/Hub/HubSIRV.py
Eir/DTMC/spatialModel/Hub/HubSIRVD.py
Eir/DTMC/spatialModel/Hub/HubSIS.py
Eir/DTMC/spatialModel/Hub/Hub_ICUV.py
Eir/DTMC/spatialModel/Hub/__init__.py
Eir/DTMC/spatialModel/PeriodicMovement/__init__.py
Eir/DTMC/spatialModel/PeriodicMovement/periodicICUV.py
Eir/DTMC/spatialModel/PeriodicMovement/periodicSEIR.py
Eir/DTMC/spatialModel/PeriodicMovement/periodicSEIRD.py
Eir/DTMC/spatialModel/PeriodicMovement/periodicSEIRDV.py
Eir/DTMC/spatialModel/PeriodicMovement/periodicSEIRS.py
Eir/DTMC/spatialModel/PeriodicMovement/periodicSEIRSD.py
Eir/DTMC/spatialModel/PeriodicMovement/periodicSEIRSDV.py
Eir/DTMC/spatialModel/PeriodicMovement/periodicSEIRV.py
Eir/DTMC/spatialModel/PeriodicMovement/periodicSEIRVS.py
Eir/DTMC/spatialModel/PeriodicMovement/periodicSIR.py
Eir/DTMC/spatialModel/PeriodicMovement/periodicSIRD.py
Eir/DTMC/spatialModel/PeriodicMovement/periodicSIRDV.py
Eir/DTMC/spatialModel/PeriodicMovement/periodicSIRS.py
Eir/DTMC/spatialModel/PeriodicMovement/periodicSIRSD.py
Eir/DTMC/spatialModel/PeriodicMovement/periodicSIRSDV.py
Eir/DTMC/spatialModel/PeriodicMovement/periodicSIRV.py
Eir/DTMC/spatialModel/PeriodicMovement/periodicSIRVS.py
Eir-0.1.21.dist-info/LICENSE
Eir-0.1.21.dist-info/METADATA
Eir-0.1.21.dist-info/WHEEL
Eir-0.1.21.dist-info/top_level.txt
Eir-0.1.21.dist-info/RECORD
