Metadata-Version: 2.1
Name: Eir
Version: 0.1.21
Summary: Helps model epidemics using spatial models
Home-page: https://github.com/mjacob1002/Eir
Author: Mathew Jacob
Author-email: mjacob1002@gmail.com
License: MIT
Download-URL: https://github.com/mjacob1002/Eir/archive/refs/tags/v_001.tar.gz
Keywords: epidemics,super spreader
Platform: UNKNOWN
Classifier: Intended Audience :: Science/Research
Classifier: License :: OSI Approved :: MIT License
Classifier: Programming Language :: Python :: 3.7
Requires-Dist: numpy
Requires-Dist: pandas
Requires-Dist: matplotlib
Requires-Dist: multipledispatch
